aiojaeger/__init__.py
aiojaeger/constants.py
aiojaeger/context_managers.py
aiojaeger/mypy_types.py
aiojaeger/py.typed
aiojaeger/record.py
aiojaeger/sampler.py
aiojaeger/span.py
aiojaeger/tracer.py
aiojaeger/transport.py
aiojaeger/utils.py
aiojaeger/version.py
aiojaeger/helpers/__init__.py
aiojaeger/helpers/aio_pika.py
aiojaeger/helpers/aiohttp.py
aiojaeger/helpers/client.py
aiojaeger/jaeger-idl/.git
aiojaeger/jaeger-idl/.gitignore
aiojaeger/jaeger-idl/.travis.yml
aiojaeger/jaeger-idl/CONTRIBUTING.md
aiojaeger/jaeger-idl/DCO
aiojaeger/jaeger-idl/LICENSE
aiojaeger/jaeger-idl/Makefile
aiojaeger/jaeger-idl/README.md
aiojaeger/jaeger-idl/.github/ISSUE_TEMPLATE.md
aiojaeger/jaeger-idl/.github/PULL_REQUEST_TEMPLATE.md
aiojaeger/jaeger-idl/proto/zipkin.proto
aiojaeger/jaeger-idl/proto/api_v2/collector.proto
aiojaeger/jaeger-idl/proto/api_v2/model.proto
aiojaeger/jaeger-idl/proto/api_v2/query.proto
aiojaeger/jaeger-idl/proto/api_v2/sampling.proto
aiojaeger/jaeger-idl/swagger/zipkin2-api.yaml
aiojaeger/jaeger-idl/thrift/agent.thrift
aiojaeger/jaeger-idl/thrift/aggregation_validator.thrift
aiojaeger/jaeger-idl/thrift/baggage.thrift
aiojaeger/jaeger-idl/thrift/dependency.thrift
aiojaeger/jaeger-idl/thrift/jaeger.thrift
aiojaeger/jaeger-idl/thrift/sampling.thrift
aiojaeger/jaeger-idl/thrift/throttling.thrift
aiojaeger/jaeger-idl/thrift/zipkincore.thrift
aiojaeger/jaeger-idl/thrift/crossdock/tracetest.thrift
aiojaeger/spancontext/__init__.py
aiojaeger/spancontext/jaeger.py
aiojaeger/spancontext/zipkin.py
tests/__init__.py
tests/conftest.py
tests/docker_fixtures.py
tests/test_aiohttp_helpers.py
tests/test_aiohttp_ingegration.py
tests/test_helpers.py
tests/test_jaeger.py
tests/test_jaeger_extract.py
tests/test_record.py
tests/test_sampler.py
tests/test_tracer.py
tests/test_transport.py
tests/test_zipkin.py
aiojaeger-0.1.8.dist-info/LICENSE
aiojaeger-0.1.8.dist-info/METADATA
aiojaeger-0.1.8.dist-info/WHEEL
aiojaeger-0.1.8.dist-info/top_level.txt
aiojaeger-0.1.8.dist-info/zip-safe
aiojaeger-0.1.8.dist-info/RECORD
