Metadata-Version: 2.1
Name: aiojaeger
Version: 0.1.8
Summary: Distributed tracing instrumentation for asyncio application with zipkin and jaeger
Home-page: https://github.com/pavkazzz/aiojaeger
Author: Pavel Mosein
Author-email: me@pavkazzz.ru
License: Apache 2
Download-URL: https://pypi.python.org/pypi/aiojaeger
Keywords: zipkin,jaeger,distributed-tracing,tracing
Platform: POSIX
Classifier: License :: OSI Approved :: MIT License
Classifier: Intended Audience :: Developers
Classifier: Programming Language :: Python :: 3
Classifier: Programming Language :: Python :: 3.7
Classifier: Programming Language :: Python :: 3.8
Classifier: Operating System :: POSIX
Classifier: Development Status :: 3 - Alpha
Classifier: Framework :: AsyncIO
Requires-Dist: aiohttp (<4)
Requires-Dist: thriftpy2 (~=0.4.11)
Requires-Dist: pydantic (~=1.4)
